{
  "expected_rows": 11,
  "predicted_rows": 11,
  "matched_rows": 11,
  "evaluated_fields": 39,
  "overall_exact_field_accuracy": 0.5385,
  "overall_character_accuracy": 0.8,
  "fields": {
    "unit_no": {
      "evaluated": 11,
      "exact_accuracy": 1.0,
      "character_accuracy": 1.0
    },
    "donor_name": {
      "evaluated": 11,
      "exact_accuracy": 0.2727,
      "character_accuracy": 0.7451
    },
    "blood_group": {
      "evaluated": 11,
      "exact_accuracy": 0.5455,
      "character_accuracy": 0.5833
    },
    "contact_no": {
      "evaluated": 6,
      "exact_accuracy": 0.1667,
      "character_accuracy": 0.8
    }
  }
}
